Metadata-Version: 1.2
Name: taint
Version: 0.0.1a1
Summary: Cryptocurrency forensics for private use
Home-page: https://gitlab.com/nolash/taint
Author: Louis Holbrook
Author-email: dev@holbrook.no
License: GPL3
Keywords: dlt,blockchain,cryptocurrency
Platform: UNKNOWN
Classifier: Programming Language :: Python :: 3
Classifier: Operating System :: OS Independent
Classifier: Development Status :: 3 - Alpha
Classifier: Environment :: Console
Classifier: Intended Audience :: Developers
Classifier: License :: OSI Approved :: GNU General Public License v3 or later (GPLv3+)
Classifier: Topic :: Internet
Requires-Python: >=3.6
